gcsa_slots/__init__.py
gcsa_slots/google_calendar.py
gcsa_slots/slots.py
gcsa_slots-0.1.1.dist-info/LICENSE
gcsa_slots-0.1.1.dist-info/METADATA
gcsa_slots-0.1.1.dist-info/WHEEL
gcsa_slots-0.1.1.dist-info/top_level.txt
gcsa_slots-0.1.1.dist-info/RECORD
