Metadata-Version: 2.1
Name: gcsa-slots
Version: 0.1.1
Summary: Simple API for Google Calendar management with slots extension (dates and times available for scheduling)
Home-page: https://github.com/leandcesar/google-calendar-simple-api-slots
Author: Leandro César Cassimiro
Author-email: ccleandroc@gmail.com
License: MIT
Keywords: python,conference,calendar,hangouts,python-library,event,conferences,google-calendar,pip,recurrence,google-calendar-api,attendee,gcsa,gcsa-slots,slots,scheduling
Platform: UNKNOWN
Classifier: License :: OSI Approved :: MIT License
Classifier: Natural Language :: English
Classifier: Programming Language :: Python
Classifier: Programming Language :: Python :: 3
Classifier: Programming Language :: Python :: 3.5
Classifier: Programming Language :: Python :: 3.6
Classifier: Programming Language :: Python :: 3.7
Classifier: Programming Language :: Python :: 3.8
Classifier: Programming Language :: Python :: 3.9
Classifier: Programming Language :: Python :: 3.10
Requires-Python: >=3.7
Requires-Dist: gcsa (>=2.0.1)
